Metadata-Version: 2.1
Name: consulta-ufv-bolivia
Version: 0.1
Summary: Este paquete le permite consultar la cotizacion de la unidad de fomento de vivienda.
Home-page: https://github.com/zxvega/consulta-ufv-bolivia
Author: Giovanni Vega
License: MIT
License-File: LICENSE
